<?xml version="1.0" encoding="UTF-8"?>
<!DOCTYPE mapper PUBLIC "-//mybatis.org//DTD Mapper 3.0//EN" "http://mybatis.org/dtd/mybatis-3-mapper.dtd">
<mapper namespace="com.ocean.dao.SharesMapper">
  <resultMap id="BaseResultMap" type="com.ocean.pojo.Shares">
    <!--
      WARNING - @mbggenerated
      This element is automatically generated by MyBatis Generator, do not modify.
    -->
    <result column="SharesCode" jdbcType="VARCHAR" property="sharescode" />
    <result column="SharesName" jdbcType="VARCHAR" property="sharesname" />
    <result column="TodayOpenPrice" jdbcType="DOUBLE" property="todayopenprice" />
    <result column="YesterdayClosingPrice" jdbcType="DOUBLE" property="yesterdayclosingprice" />
    <result column="CurrentPrice" jdbcType="DOUBLE" property="currentprice" />
    <result column="HighestPrice" jdbcType="DOUBLE" property="highestprice" />
    <result column="MinimumPrice" jdbcType="DOUBLE" property="minimumprice" />
    <result column="BuyOne" jdbcType="DOUBLE" property="buyone" />
    <result column="SellOne" jdbcType="DOUBLE" property="sellone" />
    <result column="TransactionNum" jdbcType="INTEGER" property="transactionnum" />
    <result column="TransactionMoney" jdbcType="DOUBLE" property="transactionmoney" />
    <result column="BuyOneNum" jdbcType="INTEGER" property="buyonenum" />
    <result column="BuyOnePrice" jdbcType="DOUBLE" property="buyoneprice" />
    <result column="BuyTwoNum" jdbcType="INTEGER" property="buytwonum" />
    <result column="BuyTwoPrice" jdbcType="DOUBLE" property="buytwoprice" />
    <result column="BuyThreeNum" jdbcType="INTEGER" property="buythreenum" />
    <result column="BuyThreePrice" jdbcType="DOUBLE" property="buythreeprice" />
    <result column="BuyFourNum" jdbcType="INTEGER" property="buyfournum" />
    <result column="BuyFourPrice" jdbcType="DOUBLE" property="buyfourprice" />
    <result column="BuyFiveNum" jdbcType="INTEGER" property="buyfivenum" />
    <result column="BuyFivePrice" jdbcType="DOUBLE" property="buyfiveprice" />
    <result column="SellOneNum" jdbcType="INTEGER" property="sellonenum" />
    <result column="SellOnePrice" jdbcType="DOUBLE" property="selloneprice" />
    <result column="SellTwoNum" jdbcType="INTEGER" property="selltwonum" />
    <result column="SellTwoPrice" jdbcType="DOUBLE" property="selltwoprice" />
    <result column="SellThreeNum" jdbcType="INTEGER" property="sellthreenum" />
    <result column="SellThreePrice" jdbcType="DOUBLE" property="sellthreeprice" />
    <result column="SellFourNum" jdbcType="INTEGER" property="sellfournum" />
    <result column="SellFourPrice" jdbcType="DOUBLE" property="sellfourprice" />
    <result column="SellFiveNum" jdbcType="INTEGER" property="sellfivenum" />
    <result column="SellFivePrice" jdbcType="DOUBLE" property="sellfiveprice" />
    <result column="Dates" jdbcType="VARCHAR" property="dates" />
    <result column="Times" jdbcType="VARCHAR" property="times" />
  </resultMap>
  <resultMap id="shownumMap" type="com.ocean.pojo.Shares">
    <result column="SharesCode" jdbcType="VARCHAR" property="sharescode" />
    <result column="SharesName" jdbcType="VARCHAR" property="sharesname" />
    <result column="CurrentPrice" jdbcType="DOUBLE" property="currentprice" />
  </resultMap>
  <insert id="insert" parameterType="com.ocean.pojo.Shares">
    <!--
      WARNING - @mbggenerated
      This element is automatically generated by MyBatis Generator, do not modify.
    -->
    insert into sharesinfo (SharesCode, SharesName, TodayOpenPrice, 
      YesterdayClosingPrice, CurrentPrice, HighestPrice, 
      MinimumPrice, BuyOne, SellOne, 
      TransactionNum, TransactionMoney, BuyOneNum, 
      BuyOnePrice, BuyTwoNum, BuyTwoPrice, 
      BuyThreeNum, BuyThreePrice, BuyFourNum, 
      BuyFourPrice, BuyFiveNum, BuyFivePrice, 
      SellOneNum, SellOnePrice, SellTwoNum, 
      SellTwoPrice, SellThreeNum, SellThreePrice, 
      SellFourNum, SellFourPrice, SellFiveNum, 
      SellFivePrice, Dates, Times
      )
    values (#{sharescode,jdbcType=VARCHAR}, #{sharesname,jdbcType=VARCHAR}, #{todayopenprice,jdbcType=DOUBLE}, 
      #{yesterdayclosingprice,jdbcType=DOUBLE}, #{currentprice,jdbcType=DOUBLE}, #{highestprice,jdbcType=DOUBLE}, 
      #{minimumprice,jdbcType=DOUBLE}, #{buyone,jdbcType=DOUBLE}, #{sellone,jdbcType=DOUBLE}, 
      #{transactionnum,jdbcType=INTEGER}, #{transactionmoney,jdbcType=DOUBLE}, #{buyonenum,jdbcType=INTEGER}, 
      #{buyoneprice,jdbcType=DOUBLE}, #{buytwonum,jdbcType=INTEGER}, #{buytwoprice,jdbcType=DOUBLE}, 
      #{buythreenum,jdbcType=INTEGER}, #{buythreeprice,jdbcType=DOUBLE}, #{buyfournum,jdbcType=INTEGER}, 
      #{buyfourprice,jdbcType=DOUBLE}, #{buyfivenum,jdbcType=INTEGER}, #{buyfiveprice,jdbcType=DOUBLE}, 
      #{sellonenum,jdbcType=INTEGER}, #{selloneprice,jdbcType=DOUBLE}, #{selltwonum,jdbcType=INTEGER}, 
      #{selltwoprice,jdbcType=DOUBLE}, #{sellthreenum,jdbcType=INTEGER}, #{sellthreeprice,jdbcType=DOUBLE}, 
      #{sellfournum,jdbcType=INTEGER}, #{sellfourprice,jdbcType=DOUBLE}, #{sellfivenum,jdbcType=INTEGER}, 
      #{sellfiveprice,jdbcType=DOUBLE}, #{dates,jdbcType=VARCHAR}, #{times,jdbcType=VARCHAR}
      )
  </insert>
  <insert id="insertSelective" parameterType="com.ocean.pojo.Shares">
    <!--
      WARNING - @mbggenerated
      This element is automatically generated by MyBatis Generator, do not modify.
    -->
    insert into sharesinfo
    <trim prefix="(" suffix=")" suffixOverrides=",">
      <if test="sharescode != null">
        SharesCode,
      </if>
      <if test="sharesname != null">
        SharesName,
      </if>
      <if test="todayopenprice != null">
        TodayOpenPrice,
      </if>
      <if test="yesterdayclosingprice != null">
        YesterdayClosingPrice,
      </if>
      <if test="currentprice != null">
        CurrentPrice,
      </if>
      <if test="highestprice != null">
        HighestPrice,
      </if>
      <if test="minimumprice != null">
        MinimumPrice,
      </if>
      <if test="buyone != null">
        BuyOne,
      </if>
      <if test="sellone != null">
        SellOne,
      </if>
      <if test="transactionnum != null">
        TransactionNum,
      </if>
      <if test="transactionmoney != null">
        TransactionMoney,
      </if>
      <if test="buyonenum != null">
        BuyOneNum,
      </if>
      <if test="buyoneprice != null">
        BuyOnePrice,
      </if>
      <if test="buytwonum != null">
        BuyTwoNum,
      </if>
      <if test="buytwoprice != null">
        BuyTwoPrice,
      </if>
      <if test="buythreenum != null">
        BuyThreeNum,
      </if>
      <if test="buythreeprice != null">
        BuyThreePrice,
      </if>
      <if test="buyfournum != null">
        BuyFourNum,
      </if>
      <if test="buyfourprice != null">
        BuyFourPrice,
      </if>
      <if test="buyfivenum != null">
        BuyFiveNum,
      </if>
      <if test="buyfiveprice != null">
        BuyFivePrice,
      </if>
      <if test="sellonenum != null">
        SellOneNum,
      </if>
      <if test="selloneprice != null">
        SellOnePrice,
      </if>
      <if test="selltwonum != null">
        SellTwoNum,
      </if>
      <if test="selltwoprice != null">
        SellTwoPrice,
      </if>
      <if test="sellthreenum != null">
        SellThreeNum,
      </if>
      <if test="sellthreeprice != null">
        SellThreePrice,
      </if>
      <if test="sellfournum != null">
        SellFourNum,
      </if>
      <if test="sellfourprice != null">
        SellFourPrice,
      </if>
      <if test="sellfivenum != null">
        SellFiveNum,
      </if>
      <if test="sellfiveprice != null">
        SellFivePrice,
      </if>
      <if test="dates != null">
        Dates,
      </if>
      <if test="times != null">
        Times,
      </if>
    </trim>
    <trim prefix="values (" suffix=")" suffixOverrides=",">
      <if test="sharescode != null">
        #{sharescode,jdbcType=VARCHAR},
      </if>
      <if test="sharesname != null">
        #{sharesname,jdbcType=VARCHAR},
      </if>
      <if test="todayopenprice != null">
        #{todayopenprice,jdbcType=DOUBLE},
      </if>
      <if test="yesterdayclosingprice != null">
        #{yesterdayclosingprice,jdbcType=DOUBLE},
      </if>
      <if test="currentprice != null">
        #{currentprice,jdbcType=DOUBLE},
      </if>
      <if test="highestprice != null">
        #{highestprice,jdbcType=DOUBLE},
      </if>
      <if test="minimumprice != null">
        #{minimumprice,jdbcType=DOUBLE},
      </if>
      <if test="buyone != null">
        #{buyone,jdbcType=DOUBLE},
      </if>
      <if test="sellone != null">
        #{sellone,jdbcType=DOUBLE},
      </if>
      <if test="transactionnum != null">
        #{transactionnum,jdbcType=INTEGER},
      </if>
      <if test="transactionmoney != null">
        #{transactionmoney,jdbcType=DOUBLE},
      </if>
      <if test="buyonenum != null">
        #{buyonenum,jdbcType=INTEGER},
      </if>
      <if test="buyoneprice != null">
        #{buyoneprice,jdbcType=DOUBLE},
      </if>
      <if test="buytwonum != null">
        #{buytwonum,jdbcType=INTEGER},
      </if>
      <if test="buytwoprice != null">
        #{buytwoprice,jdbcType=DOUBLE},
      </if>
      <if test="buythreenum != null">
        #{buythreenum,jdbcType=INTEGER},
      </if>
      <if test="buythreeprice != null">
        #{buythreeprice,jdbcType=DOUBLE},
      </if>
      <if test="buyfournum != null">
        #{buyfournum,jdbcType=INTEGER},
      </if>
      <if test="buyfourprice != null">
        #{buyfourprice,jdbcType=DOUBLE},
      </if>
      <if test="buyfivenum != null">
        #{buyfivenum,jdbcType=INTEGER},
      </if>
      <if test="buyfiveprice != null">
        #{buyfiveprice,jdbcType=DOUBLE},
      </if>
      <if test="sellonenum != null">
        #{sellonenum,jdbcType=INTEGER},
      </if>
      <if test="selloneprice != null">
        #{selloneprice,jdbcType=DOUBLE},
      </if>
      <if test="selltwonum != null">
        #{selltwonum,jdbcType=INTEGER},
      </if>
      <if test="selltwoprice != null">
        #{selltwoprice,jdbcType=DOUBLE},
      </if>
      <if test="sellthreenum != null">
        #{sellthreenum,jdbcType=INTEGER},
      </if>
      <if test="sellthreeprice != null">
        #{sellthreeprice,jdbcType=DOUBLE},
      </if>
      <if test="sellfournum != null">
        #{sellfournum,jdbcType=INTEGER},
      </if>
      <if test="sellfourprice != null">
        #{sellfourprice,jdbcType=DOUBLE},
      </if>
      <if test="sellfivenum != null">
        #{sellfivenum,jdbcType=INTEGER},
      </if>
      <if test="sellfiveprice != null">
        #{sellfiveprice,jdbcType=DOUBLE},
      </if>
      <if test="dates != null">
        #{dates,jdbcType=VARCHAR},
      </if>
      <if test="times != null">
        #{times,jdbcType=VARCHAR},
      </if>
    </trim>
  </insert>
  <select id="findShares" resultType="com.ocean.pojo.Shares">
    select top 10 * from sharesinfo
  </select>
  <select id="sharestop" statementType="STATEMENT" resultType="hashmap" parameterType="int">
     select top ${top}  sharescode,sharesname,currentprice from sharesinfo
  </select>

</mapper>
